README.md
setup.py
padivinanza/__init__.py
padivinanza/adivina.py
padivinanza.egg-info/PKG-INFO
padivinanza.egg-info/SOURCES.txt
padivinanza.egg-info/dependency_links.txt
padivinanza.egg-info/entry_points.txt
padivinanza.egg-info/top_level.txt