Metadata-Version: 1.0
Name: padivinanza
Version: 0.2
Summary: Una adivinanza
Home-page: http://github.com/julvez/padivinanza
Author: Jorge Julvez
Author-email: julvez@unizar.es
License: GNU GENERAL PUBLIC LICENSE
Keywords: advinanzas riddles
Platform: UNKNOWN
